lino_book/__init__.py
lino_book/setup_info.py
lino_book/projects/__init__.py
lino_book/projects/actions/__init__.py
lino_book/projects/actions/manage.py
lino_book/projects/actions/models.py
lino_book/projects/actions/settings.py
lino_book/projects/actors/__init__.py
lino_book/projects/actors/manage.py
lino_book/projects/actors/models.py
lino_book/projects/actors/settings.py
lino_book/projects/actors/ui.py
lino_book/projects/actors/fixtures/__init__.py
lino_book/projects/actors/fixtures/demo.py
lino_book/projects/addrloc/__init__.py
lino_book/projects/addrloc/manage.py
lino_book/projects/addrloc/models.py
lino_book/projects/addrloc/settings.py
lino_book/projects/addrloc/ui.py
lino_book/projects/addrloc/fixtures/__init__.py
lino_book/projects/addrloc/fixtures/demo.py
lino_book/projects/anna/__init__.py
lino_book/projects/anna/initdb_tmp
lino_book/projects/anna/manage.py
lino_book/projects/anna/user_types.py
lino_book/projects/anna/lib/__init__.py
lino_book/projects/anna/lib/tickets/__init__.py
lino_book/projects/anna/lib/tickets/models.py
lino_book/projects/anna/settings/__init__.py
lino_book/projects/anna/settings/demo.py
lino_book/projects/anna/settings/doctests.py
lino_book/projects/anna/settings/memory.py
lino_book/projects/anna/settings/www.py
lino_book/projects/anna/tests/__init__.py
lino_book/projects/anna/tests/test_cascaded_delete.py
lino_book/projects/auto_create/__init__.py
lino_book/projects/auto_create/manage.py
lino_book/projects/auto_create/models.py
lino_book/projects/auto_create/settings.py
lino_book/projects/avanti1/__init__.py
lino_book/projects/avanti1/initdb_tmp
lino_book/projects/avanti1/manage.py
lino_book/projects/avanti1/settings.py
lino_book/projects/avanti1/startup.py
lino_book/projects/avanti1/config/weasyprint/top-right.jpg
lino_book/projects/avanti1/config/weasyprint/top-right.xcf
lino_book/projects/avanti1/fixtures/__init__.py
lino_book/projects/avanti1/fixtures/demo.py
lino_book-25.7.0.dist-info/METADATA
lino_book-25.7.0.dist-info/WHEEL
lino_book-25.7.0.dist-info/licenses/AUTHORS.rst
lino_book-25.7.0.dist-info/licenses/COPYING
lino_book-25.7.0.dist-info/RECORD
