Metadata-Version: 2.4
Name: lino_book
Version: 25.7.0
Summary: Lino Developer documentation and demo projects
Project-URL: Repository, https://gitlab.com/lino-framework/book
Project-URL: Homepage, https://dev.lino-framework.org
Author-email: Rumma & Ko Ltd <info@saffre-rumma.net>, Luc Saffre <luc@saffre-rumma.net>
License:                     GNU AFFERO GENERAL PUBLIC LICENSE
License-File: AUTHORS.rst
License-File: COPYING
Keywords: Django,React,customized,framework
Classifier: Development Status :: 5 - Production/Stable
Classifier: Environment :: Web Environment
Classifier: Framework :: Django
Classifier: Intended Audience :: Developers
Classifier: Intended Audience :: System Administrators
Classifier: License :: OSI Approved :: GNU Affero General Public License v3
Classifier: Natural Language :: English
Classifier: Natural Language :: French
Classifier: Natural Language :: German
Classifier: Operating System :: OS Independent
Classifier: Programming Language :: Python
Classifier: Programming Language :: Python :: 3
Classifier: Topic :: Database :: Front-Ends
Classifier: Topic :: Office/Business
Classifier: Topic :: Software Development :: Libraries :: Application Frameworks
Requires-Python: >=3.8
Requires-Dist: beautifulsoup4
Requires-Dist: commondata
Requires-Dist: django-iban
Requires-Dist: django-wkhtmltopdf
Requires-Dist: djangorestframework
Requires-Dist: docutils
Requires-Dist: icalendar
Requires-Dist: metafone
Requires-Dist: mock
Requires-Dist: radicale
Requires-Dist: reportlab
Requires-Dist: selenium
Requires-Dist: sqlparse
Requires-Dist: vobject
Provides-Extra: testing
Requires-Dist: atelier; extra == 'testing'
Requires-Dist: hatch; extra == 'testing'
Requires-Dist: pytest; extra == 'testing'
Requires-Dist: pytest-cov; extra == 'testing'
Requires-Dist: pytest-env; extra == 'testing'
Requires-Dist: pytest-forked; extra == 'testing'
Requires-Dist: pytest-html; extra == 'testing'
